pyxem/__init__.py
pyxem/common.py
pyxem/conftest.py
pyxem/hyperspy_extension.yaml
pyxem/release_info.py
pyxem/components/__init__.py
pyxem/components/reduced_intensity_correction_component.py
pyxem/components/scattering_fit_component_lobato.py
pyxem/components/scattering_fit_component_xtables.py
pyxem/data/__init__.py
pyxem/data/_data.py
pyxem/data/_registry.py
pyxem/data/simulated_dpc.py
pyxem/data/simulated_fe.py
pyxem/data/simulated_overlap.py
pyxem/data/simulated_si.py
pyxem/data/simulated_strain.py
pyxem/data/simulated_tilt.py
pyxem/data/dummy_data/__init__.py
pyxem/data/dummy_data/dummy_data.py
pyxem/data/dummy_data/make_diffraction_test_data.py
pyxem/data/dummy_data/make_overlapping_nanocrystals.py
pyxem/data/test/__init__.py
pyxem/data/test/test_data.py
pyxem/generators/__init__.py
pyxem/generators/calibration_generator.py
pyxem/generators/displacement_gradient_tensor_generator.py
pyxem/generators/indexation_generator.py
pyxem/generators/integration_generator.py
pyxem/generators/pdf_generator1d.py
pyxem/generators/red_intensity_generator1d.py
pyxem/generators/subpixelrefinement_generator.py
pyxem/generators/variance_generator.py
pyxem/generators/virtual_image_generator.py
pyxem/libraries/__init__.py
pyxem/libraries/calibration_library.py
pyxem/signals/__init__.py
pyxem/signals/beam_shift.py
pyxem/signals/common_diffraction.py
pyxem/signals/correlation1d.py
pyxem/signals/correlation2d.py
pyxem/signals/differential_phase_contrast.py
pyxem/signals/diffraction1d.py
pyxem/signals/diffraction2d.py
pyxem/signals/diffraction_variance1d.py
pyxem/signals/diffraction_variance2d.py
pyxem/signals/diffraction_vectors.py
pyxem/signals/diffraction_vectors1d.py
pyxem/signals/diffraction_vectors2d.py
pyxem/signals/electron_diffraction1d.py
pyxem/signals/electron_diffraction2d.py
pyxem/signals/indexation_results.py
pyxem/signals/insitu_diffraction2d.py
pyxem/signals/labeled_diffraction_vectors2d.py
pyxem/signals/pair_distribution_function1d.py
pyxem-0.21.0.dist-info/licenses/LICENSE
pyxem-0.21.0.dist-info/METADATA
pyxem-0.21.0.dist-info/WHEEL
pyxem-0.21.0.dist-info/entry_points.txt
pyxem-0.21.0.dist-info/top_level.txt
pyxem-0.21.0.dist-info/RECORD
