Metadata-Version: 2.4
Name: pyxem
Version: 0.21.0
Summary: multi-dimensional diffraction microscopy
Home-page: https://github.com/pyxem/pyxem
Author: Duncan Johnstone, Phillip Crout, Carter Francis, Magnus Nord
Author-email: pyxem.team@gmail.com
License: GPLv3+
Keywords: data analysis,diffraction,microscopy,electron diffraction,electron microscopy
Classifier: Programming Language :: Python :: 3
Classifier: Programming Language :: Python :: 3.7
Classifier: Programming Language :: Python :: 3.8
Classifier: Programming Language :: Python :: 3.9
Classifier: Programming Language :: Python :: 3.10
Classifier: Programming Language :: Python :: 3.11
Classifier: Development Status :: 4 - Beta
Classifier: Intended Audience :: Science/Research
Classifier: License :: OSI Approved :: GNU General Public License v3 (GPLv3)
Classifier: Natural Language :: English
Classifier: Operating System :: OS Independent
Classifier: Topic :: Scientific/Engineering
Classifier: Topic :: Scientific/Engineering :: Physics
Requires-Python: >=3.7
License-File: LICENSE
Requires-Dist: dask
Requires-Dist: diffsims>=0.7.0
Requires-Dist: hyperspy>=2.0
Requires-Dist: h5py
Requires-Dist: lmfit>=0.9.12
Requires-Dist: matplotlib>=3.7.5
Requires-Dist: numba
Requires-Dist: numpy
Requires-Dist: orix>=0.12.1
Requires-Dist: pooch
Requires-Dist: psutil
Requires-Dist: scikit-image!=0.21.0,>=0.19.0
Requires-Dist: scikit-learn>=1.0
Requires-Dist: shapely>2.0.0
Requires-Dist: scipy
Requires-Dist: tqdm
Requires-Dist: traits
Requires-Dist: transforms3d
Requires-Dist: zarr<3.0.0
Provides-Extra: doc
Requires-Dist: nbsphinx>=0.7; extra == "doc"
Requires-Dist: sphinx>=3.0.2; extra == "doc"
Requires-Dist: sphinx-copybutton>=0.2.5; extra == "doc"
Requires-Dist: sphinx-autodoc-typehints>=1.10.3; extra == "doc"
Requires-Dist: sphinx-gallery>=0.6; extra == "doc"
Requires-Dist: sphinxcontrib-bibtex>=1.0; extra == "doc"
Requires-Dist: sphinx_design; extra == "doc"
Requires-Dist: sphinx-codeautolink; extra == "doc"
Requires-Dist: pydata-sphinx-theme; extra == "doc"
Requires-Dist: hyperspy_gui_ipywidgets>=2.0; extra == "doc"
Requires-Dist: dask-image; extra == "doc"
Provides-Extra: tests
Requires-Dist: pytest>=5.0; extra == "tests"
Requires-Dist: pytest-timeout; extra == "tests"
Requires-Dist: pytest-cov>=2.8.1; extra == "tests"
Requires-Dist: pytest-xdist; extra == "tests"
Requires-Dist: pytest-rerunfailures; extra == "tests"
Requires-Dist: coveralls>=1.10; extra == "tests"
Requires-Dist: coverage>=5.0; extra == "tests"
Provides-Extra: dev
Requires-Dist: black~=24.1; extra == "dev"
Requires-Dist: pre-commit>=1.16; extra == "dev"
Provides-Extra: gpu
Requires-Dist: cupy>=9.0.0; extra == "gpu"
Provides-Extra: dask
Requires-Dist: dask-image; extra == "dask"
Requires-Dist: distributed; extra == "dask"
Dynamic: author
Dynamic: author-email
Dynamic: classifier
Dynamic: description
Dynamic: home-page
Dynamic: keywords
Dynamic: license
Dynamic: license-file
Dynamic: provides-extra
Dynamic: requires-dist
Dynamic: requires-python
Dynamic: summary
